neo4j_python_migrations/__init__.py
neo4j_python_migrations/__main__.py
neo4j_python_migrations/analyzer.py
neo4j_python_migrations/cli.py
neo4j_python_migrations/dao.py
neo4j_python_migrations/executor.py
neo4j_python_migrations/loader.py
neo4j_python_migrations/migration.py
neo4j_python_migrations-0.1.4.dist-info/METADATA
neo4j_python_migrations-0.1.4.dist-info/WHEEL
neo4j_python_migrations-0.1.4.dist-info/licenses/LICENSE
neo4j_python_migrations-0.1.4.dist-info/RECORD
