Metadata-Version: 2.4
Name: neo4j-python-migrations
Version: 0.1.4
Summary: A database migration tool for Neo4j that allows to apply Cypher-based and arbitrary Python-based migrations.
Project-URL: Repository, https://github.com/booqoffsky/neo4j-python-migrations
Author-email: Grigory Bukovsky <booqoffsky@yandex.ru>
License-Expression: MIT
License-File: LICENSE
Keywords: migrations,migrator,neo4j,python
Classifier: Programming Language :: Python
Classifier: Programming Language :: Python :: 3
Classifier: Programming Language :: Python :: 3 :: Only
Classifier: Programming Language :: Python :: 3.10
Classifier: Programming Language :: Python :: 3.11
Classifier: Programming Language :: Python :: 3.12
Classifier: Programming Language :: Python :: 3.13
Classifier: Programming Language :: Python :: 3.14
Requires-Python: >=3.10
Requires-Dist: neo4j>=5
Requires-Dist: packaging>=24
Requires-Dist: typer<1,>=0
Requires-Dist: yarl<2,>=1
